dmPython.cp36-win_amd64.pyd
dmPython-8.1.2.98.dist-info/METADATA
dmPython-8.1.2.98.dist-info/WHEEL
dmPython-8.1.2.98.dist-info/top_level.txt
dmPython-8.1.2.98.dist-info/RECORD
