Metadata-Version: 2.1
Name: dmPython
Version: 8.1.2.98
Summary: Python interface to Dameng
Home-page: UNKNOWN
Author: UNKNOWN
Author-email: UNKNOWN
License: Python Software Foundation License
Keywords: Dameng
Platform: UNKNOWN
Classifier: Development Status :: 4 - Beta
Classifier: Intended Audience :: Developers
Classifier: Programming Language :: Python :: 3.6
Classifier: Topic :: Database
